ecommercedesirability3/cli.py
ecommercedesirability3/dataset.py
ecommercedesirability3-0.1.3.dist-info/METADATA
ecommercedesirability3-0.1.3.dist-info/WHEEL
ecommercedesirability3-0.1.3.dist-info/entry_points.txt
ecommercedesirability3-0.1.3.dist-info/top_level.txt
ecommercedesirability3-0.1.3.dist-info/RECORD
